dog.py
dog-14.data/scripts/dog.py
dog-14.dist-info/LICENSE
dog-14.dist-info/METADATA
dog-14.dist-info/WHEEL
dog-14.dist-info/entry_points.txt
dog-14.dist-info/top_level.txt
dog-14.dist-info/RECORD
