Metadata-Version: 2.1
Name: dog
Version: 14
Summary: dog is a simple wrapper for "docker run" to make it simple to call tools residing inside docker containers
Home-page: https://github.com/rasmus-toftdahl-olesen/dog
Author: Rasmus Toftdahl Olesen
Author-email: rasmus.toftdahl.olesen@gmail.com
License: The Unlicense
Platform: any
Classifier: Operating System :: OS Independent
Classifier: License :: OSI Approved :: The Unlicense (Unlicense)
Classifier: Environment :: Console
Classifier: Topic :: Software Development :: Build Tools
Classifier: Topic :: Software Development :: Embedded Systems
Classifier: Programming Language :: Python :: 3
Requires-Python: >=3.5
License-File: LICENSE
